popcoder/__init__.py
popcoder/editor.py
popcoder/popcoder.py
popcoder/util.py
popcoder/video.py
popcoder/tests/__init__.py
popcoder/tests/test_editor.py
popcoder/tests/test_main.py
popcoder/tests/test_util.py
popcoder/tests/test_video.py
popcoder-0.1.2.dist-info/top_level.txt
popcoder-0.1.2.dist-info/entry_points.txt
popcoder-0.1.2.dist-info/METADATA
popcoder-0.1.2.dist-info/DESCRIPTION.rst
popcoder-0.1.2.dist-info/metadata.json
popcoder-0.1.2.dist-info/WHEEL
popcoder-0.1.2.dist-info/RECORD
