Metadata-Version: 2.0
Name: popcoder
Version: 0.1.2
Summary: Python library for transcoding popcorn code into flat video files
Home-page: https://github.com/mozilla/popcoder
Author: Mike Nolan
Author-email: me@michael-nolan.com
License: Mozilla Public License 2.0 (MPL 2.0)
Platform: UNKNOWN
Classifier: License :: OSI Approved :: Mozilla Public License 2.0 (MPL 2.0)
Classifier: Operating System :: OS Independent
Classifier: Programming Language :: Python :: 2.7
Classifier: Topic :: Software Development :: Libraries :: Python Modules
